setup.py
chat_client/__init__.py
chat_client/client_main.py
chat_client/client/__init__.py
chat_client/client/add_contact.py
chat_client/client/client_database.py
chat_client/client/client_gui.py
chat_client/client/client_transport.py
chat_client/client/del_contact.py
chat_client/client/main_window.py
chat_client/client/start_dialog.py
chat_client/common/__init__.py
chat_client/common/cpypt.py
chat_client/common/utils.py
chat_client/common/config/__init__.py
chat_client/common/config/codes.py
chat_client/common/config/methods.py
chat_client/common/config/system.py
chat_client/common/log/__init__.py
chat_client/common/log/client_log_config.py
chat_client/common/log/server_log_config.py
chat_client/docs/__init__.py
chat_client/docs/source/__init__.py
chat_client/docs/source/conf.py
chat_client/tests/__init__.py
chat_client/tests/test_client.py
chat_client/tests/test_utils.py
mess_chat_client_gb.egg-info/PKG-INFO
mess_chat_client_gb.egg-info/SOURCES.txt
mess_chat_client_gb.egg-info/dependency_links.txt
mess_chat_client_gb.egg-info/requires.txt
mess_chat_client_gb.egg-info/top_level.txt