Metadata-Version: 1.0
Name: mess-chat-client-gb
Version: 0.0.1
Summary: mess_chat_client_gb
Home-page: UNKNOWN
Author: Pavel Stefanenko
Author-email: p.stefanenko@gmail.com
License: UNKNOWN
Platform: UNKNOWN
